timeweb/__init__.py
timeweb/__meta.py
timeweb/async_api/__init__.py
timeweb/async_api/account.py
timeweb/async_api/api.py
timeweb/async_api/balancers.py
timeweb/async_api/base.py
timeweb/async_api/dbs.py
timeweb/async_api/dedics.py
timeweb/async_api/domains.py
timeweb/async_api/images.py
timeweb/async_api/k8s.py
timeweb/async_api/mail.py
timeweb/async_api/projects.py
timeweb/async_api/s3.py
timeweb/async_api/ssh_keys.py
timeweb/async_api/tokens.py
timeweb/async_api/vds.py
timeweb/errors/__init__.py
timeweb/errors/exc.py
timeweb/schemas/__init__.py
timeweb/schemas/account/__init__.py
timeweb/schemas/account/access.py
timeweb/schemas/account/countries.py
timeweb/schemas/account/finances.py
timeweb/schemas/account/ips.py
timeweb/schemas/account/status.py
timeweb/schemas/balancers/__init__.py
timeweb/schemas/balancers/balancers.py
timeweb/schemas/balancers/presets.py
timeweb/schemas/base.py
timeweb/schemas/dbs/__init__.py
timeweb/schemas/dbs/backups.py
timeweb/schemas/dbs/dbs.py
timeweb/schemas/dbs/presets.py
timeweb/schemas/domains/__init__.py
timeweb/schemas/domains/dns.py
timeweb/schemas/domains/domains.py
timeweb/schemas/domains/ns.py
timeweb/schemas/domains/requests.py
timeweb/schemas/domains/tld.py
timeweb/schemas/errors.py
timeweb/schemas/images/__init__.py
timeweb/schemas/images/images.py
timeweb/schemas/kubernetes/__init__.py
timeweb/schemas/kubernetes/kubernetes.py
timeweb/schemas/kubernetes/nodes.py
timeweb/schemas/kubernetes/resources.py
timeweb/schemas/mail/__init__.py
timeweb/schemas/mail/mail.py
timeweb/schemas/projects/__init__.py
timeweb/schemas/projects/models.py
timeweb/schemas/projects/responses.py
timeweb/schemas/s3/__init__.py
timeweb/schemas/s3/objects.py
timeweb/schemas/s3/presets.py
timeweb/schemas/s3/s3.py
timeweb/schemas/s3/subdomains.py
timeweb/schemas/s3/transfer.py
timeweb/schemas/s3/users.py
timeweb/schemas/servers/__init__.py
timeweb/schemas/servers/cloud/__init__.py
timeweb/schemas/servers/cloud/backup.py
timeweb_cloud-0.12.2.dist-info/LICENSE
timeweb_cloud-0.12.2.dist-info/METADATA
timeweb_cloud-0.12.2.dist-info/WHEEL
timeweb_cloud-0.12.2.dist-info/RECORD
