Metadata-Version: 2.1
Name: timeweb-cloud
Version: 0.12.2
Summary: Timeweb Cloud API wrapper
Home-page: https://github.com/LulzLoL231/timeweb-cloud
License: MIT
Keywords: timeweb,timeweb.cloud,api,wrapper
Author: Maxim Mosin
Author-email: max@mosin.pw
Requires-Python: >=3.10,<4.0
Classifier: Development Status :: 4 - Beta
Classifier: Intended Audience :: Developers
Classifier: License :: OSI Approved :: MIT License
Classifier: Operating System :: OS Independent
Classifier: Programming Language :: Python :: 3
Classifier: Programming Language :: Python :: 3.10
Classifier: Programming Language :: Python :: 3.11
Classifier: Programming Language :: Python :: 3
Classifier: Programming Language :: Python :: 3.10
Classifier: Topic :: Software Development :: Libraries :: Python Modules
Requires-Dist: httpx (>=0.23.3,<0.24.0)
Requires-Dist: isodate (>=0.6.1,<0.7.0)
Requires-Dist: pydantic (>=1.10.4,<2.0.0)
Project-URL: Repository, https://github.com/LulzLoL231/timeweb-cloud
